openstef_core/__init__.py
openstef_core/base_model.py
openstef_core/exceptions.py
openstef_core/testing.py
openstef_core/types.py
openstef_core/datasets/__init__.py
openstef_core/datasets/mixins.py
openstef_core/datasets/timeseries_dataset.py
openstef_core/datasets/validated_datasets.py
openstef_core/datasets/validation.py
openstef_core/datasets/versioned_timeseries_dataset.py
openstef_core/mixins/__init__.py
openstef_core/mixins/predictor.py
openstef_core/mixins/stateful.py
openstef_core/mixins/transform.py
openstef_core/transforms/__init__.py
openstef_core/transforms/dataset_transforms.py
openstef_core/utils/__init__.py
openstef_core/utils/datetime.py
openstef_core/utils/invariants.py
openstef_core/utils/itertools.py
openstef_core/utils/multiprocessing.py
openstef_core/utils/pandas.py
openstef_core/utils/pydantic.py
openstef_core-4.0.0a10.dist-info/METADATA
openstef_core-4.0.0a10.dist-info/WHEEL
openstef_core-4.0.0a10.dist-info/RECORD
