Metadata-Version: 2.4
Name: openstef-core
Version: 4.0.0a10
Summary: Core functionality for OpenSTEF, a framework for short-term energy forecasting.
Project-URL: Documentation, https://openstef.github.io/openstef/index.html
Project-URL: Homepage, https://lfenergy.org/projects/openstef/
Project-URL: Issues, https://github.com/OpenSTEF/openstef/issues
Project-URL: Repository, https://github.com/OpenSTEF/openstef
Author-email: "Alliander N.V" <openstef@lfenergy.org>
License-Expression: MPL-2.0
Keywords: energy,forecasting,machinelearning
Classifier: Development Status :: 5 - Production/Stable
Classifier: Intended Audience :: Developers
Classifier: Programming Language :: Python :: 3 :: Only
Classifier: Programming Language :: Python :: 3.12
Classifier: Programming Language :: Python :: 3.13
Classifier: Programming Language :: Python :: 3.14
Requires-Python: <4.0,>=3.12
Requires-Dist: joblib<2,>=1
Requires-Dist: numpy<3,>=2.3.2
Requires-Dist: pandas<3,>=2.3.1
Requires-Dist: pyarrow>=21
Requires-Dist: pydantic-extra-types<3,>=2.10.5
Requires-Dist: pydantic<3,>=2.12.4
